parseq_analyze/__init__.py
parseq_analyze/align.py
parseq_analyze/consensus.py
parseq_analyze/demultiplex.py
parseq_analyze/initialize.py
parseq_analyze/raw_file_processing.py
parseq_analyze/run_parseq.py
parseq_analyze/utils.py
parseq_analyze/visualizations.py
parseq_analyze-0.1.1.dist-info/LICENSE
parseq_analyze-0.1.1.dist-info/METADATA
parseq_analyze-0.1.1.dist-info/WHEEL
parseq_analyze-0.1.1.dist-info/top_level.txt
parseq_analyze-0.1.1.dist-info/RECORD
